revel2d2l/__init__.py
revel2d2l/revel2d2l.py
revel2d2l-0.3.0.dist-info/entry_points.txt
revel2d2l-0.3.0.dist-info/LICENSE
revel2d2l-0.3.0.dist-info/WHEEL
revel2d2l-0.3.0.dist-info/METADATA
revel2d2l-0.3.0.dist-info/RECORD
