Metadata-Version: 2.1
Name: revel2d2l
Version: 0.3.0
Summary: Import Revel grade data into D2L LMS
Home-page: https://github.com/datagazing/revel2d2l
Author: Brendan Strejcek
Author-email: brendan@datagazing.com
Requires-Python: >=3.7
Classifier: License :: OSI Approved :: MIT License
Requires-Dist: Levenshtein
Requires-Dist: monist
Requires-Dist: pandas
Requires-Dist: pandasql
Requires-Dist: PyYAML
